scrapli_asyncssh/__init__.py
scrapli_asyncssh/transport/__init__.py
scrapli_asyncssh/transport/asyncssh_.py
tests/__init__.py
tests/test_data/__init__.py
tests/test_data/files/__init__.py
tests/unit/__init__.py
tests/unit/transport/__init__.py
tests/unit/transport/test_asyncssh_.py
scrapli_asyncssh-2020.12.23.dist-info/LICENSE
scrapli_asyncssh-2020.12.23.dist-info/METADATA
scrapli_asyncssh-2020.12.23.dist-info/WHEEL
scrapli_asyncssh-2020.12.23.dist-info/top_level.txt
scrapli_asyncssh-2020.12.23.dist-info/RECORD
