Metadata-Version: 2.1
Name: scrapli-asyncssh
Version: 2020.12.23
Summary: asyncssh transport plugin for the scrapli SSH|Telnet screen scraping library
Home-page: https://github.com/scrapli/scrapli_asyncssh
Author: Carl Montanari
Author-email: carl.r.montanari@gmail.com
License: MIT
Project-URL: Changelog, https://github.com/scrapli/scrapli_asyncssh/blob/master/CHANGELOG.md
Platform: UNKNOWN
Classifier: License :: OSI Approved :: MIT License
Classifier: Operating System :: POSIX :: Linux
Classifier: Operating System :: MacOS
Classifier: Programming Language :: Python
Classifier: Programming Language :: Python :: 3.6
Classifier: Programming Language :: Python :: 3.7
Classifier: Programming Language :: Python :: 3.8
Classifier: Programming Language :: Python :: 3.9
Classifier: Programming Language :: Python :: 3 :: Only
Classifier: Topic :: Software Development :: Libraries :: Python Modules
Requires-Python: >=3.6
